[
  {
    "author": "LMB Studio",
    "link_thumb": "https://live.staticflickr.com/65535/51673657103_d97a9244a8_o.gif",
    "link_bin": "https://github.com/lmbstudiocontact/mb4_35/raw/main/Butterfly_L7_-1762492723.bin",
    "id_bin": "Butterfly_L7_-1762492723",
    "list_language": [],
    "array_tags": [
      "lmbstudio"
    ],
    "list_album": [
      {
        "id_album": "657564375",
        "link_thumb": "https://live.staticflickr.com/65535/51673657103_d97a9244a8_o.gif",
        "title": "Butterfly_L7"
      }
    ]
  },
  {
    "author": "adamkhoa253",
    "link_thumb": "https://live.staticflickr.com/65535/51671687307_ab3688dfb8_o.gif",
    "link_bin": "https://github.com/lmbstudiocontact/mb4_11/raw/main/9659.bin",
    "id_bin": "9659",
    "list_language": [],
    "array_tags": [
      "date",
      "seconds",
      "floors",
      "distance",
      "heartrate",
      "calories",
      "battery",
      "steps"
    ],
    "list_album": [
      {
        "id_album": "-975585370",
        "link_thumb": "https://live.staticflickr.com/65535/51671687307_ab3688dfb8_o.gif",
        "title": "Other 1_Animation"
      }
    ]
  },
  {
    "author": "LMB Studio",
    "link_thumb": "https://live.staticflickr.com/65535/51688705979_391924d31d_o.gif",
    "link_bin": "https://github.com/lmbstudiocontact/mb4_81/raw/main/Seven deadly sins Anime_L10_1050137721.bin",
    "id_bin": "Seven deadly sins Anime_L10_1050137721",
    "list_language": [
      {
        "author": "LMB Studio",
        "link_thumb": "https://live.staticflickr.com/65535/51687236122_256d59236e_o.gif",
        "link_bin": "https://github.com/lmbstudiocontact/mb4_81/raw/main/Seven deadly sins Anime_L10_1050137721_English.bin",
        "name_language": "English",
        "id_bin_language": "Seven deadly sins Anime_L10_1050137721_English"
      },
      {
        "author": "LMB Studio",
        "link_thumb": "https://live.staticflickr.com/65535/51688706319_3ffc7e97e6_o.gif",
        "link_bin": "https://github.com/lmbstudiocontact/mb4_81/raw/main/Seven deadly sins Anime_L10_1050137721_Portuguese.bin",
        "name_language": "Portuguese",
        "id_bin_language": "Seven deadly sins Anime_L10_1050137721_Portuguese"
      },
      {
        "author": "LMB Studio",
        "link_thumb": "https://live.staticflickr.com/65535/51688706479_6b7ba8617b_o.gif",
        "link_bin": "https://github.com/lmbstudiocontact/mb4_81/raw/main/Seven deadly sins Anime_L10_1050137721_Russian.bin",
        "name_language": "Russian",
        "id_bin_language": "Seven deadly sins Anime_L10_1050137721_Russian"
      },
      {
        "author": "LMB Studio",
        "link_thumb": "https://live.staticflickr.com/65535/51688027051_86f1286f38_o.gif",
        "link_bin": "https://github.com/lmbstudiocontact/mb4_81/raw/main/Seven deadly sins Anime_L10_1050137721_Spanish.bin",
        "name_language": "Spanish",
        "id_bin_language": "Seven deadly sins Anime_L10_1050137721_Spanish"
      }
    ],
    "array_tags": [
      "lmbstudio"
    ],
    "list_album": [
      {
        "id_album": "33964247",
        "link_thumb": "https://live.staticflickr.com/65535/51688705979_391924d31d_o.gif",
        "title": "Seven deadly sins Anime_L10"
      }
    ]
  },
  {
    "author": "1luanmelo",
    "link_thumb": "https://live.staticflickr.com/65535/51673660457_36886fabb4_o.gif",
    "link_bin": "https://github.com/lmbstudiocontact/mb4_10/raw/main/6600.bin",
    "id_bin": "6600",
    "list_language": [],
    "array_tags": [
      "digital"
    ],
    "list_album": [
      {
        "id_album": "80085222",
        "link_thumb": "https://live.staticflickr.com/65535/51673660457_36886fabb4_o.gif",
        "title": "Space"
      }
    ]
  },
  {
    "author": "mjmf84",
    "link_thumb": "https://live.staticflickr.com/65535/51671068337_eab28bb6e0_o.gif",
    "link_bin": "https://github.com/lmbstudiocontact/mb4_6/raw/main/3695.bin",
    "id_bin": "3695",
    "list_language": [],
    "array_tags": [],
    "list_album": [
      {
        "id_album": "1381221108",
        "link_thumb": "https://live.staticflickr.com/65535/51671068337_eab28bb6e0_o.gif",
        "title": "Football Old"
      }
    ]
  },
  {
    "author": "LMB Studio",
    "link_thumb": "https://live.staticflickr.com/65535/51683524430_19c3361662_o.gif",
    "link_bin": "https://github.com/lmbstudiocontact/mb4_60/raw/main/One Piece Anime_L10_-594695653.bin",
    "id_bin": "One Piece Anime_L10_-594695653",
    "list_language": [
      {
        "author": "LMB Studio",
        "link_thumb": "https://live.staticflickr.com/65535/51682894278_cc2807a722_o.gif",
        "link_bin": "https://github.com/lmbstudiocontact/mb4_60/raw/main/One Piece Anime_L10_-594695653_English.bin",
        "name_language": "English",
        "id_bin_language": "One Piece Anime_L10_-594695653_English"
      },
      {
        "author": "LMB Studio",
        "link_thumb": "https://live.staticflickr.com/65535/51683524815_6cbb898a23_o.gif",
        "link_bin": "https://github.com/lmbstudiocontact/mb4_60/raw/main/One Piece Anime_L10_-594695653_Portuguese.bin",
        "name_language": "Portuguese",
        "id_bin_language": "One Piece Anime_L10_-594695653_Portuguese"
      },
      {
        "author": "LMB Studio",
        "link_thumb": "https://live.staticflickr.com/65535/51682635521_9621affce5_o.gif",
        "link_bin": "https://github.com/lmbstudiocontact/mb4_60/raw/main/One Piece Anime_L10_-594695653_Russian.bin",
        "name_language": "Russian",
        "id_bin_language": "One Piece Anime_L10_-594695653_Russian"
      },
      {
        "author": "LMB Studio",
        "link_thumb": "https://live.staticflickr.com/65535/51683525245_9ee57da895_o.gif",
        "link_bin": "https://github.com/lmbstudiocontact/mb4_60/raw/main/One Piece Anime_L10_-594695653_Spanish.bin",
        "name_language": "Spanish",
        "id_bin_language": "One Piece Anime_L10_-594695653_Spanish"
      }
    ],
    "array_tags": [
      "lmbstudio"
    ],
    "list_album": [
      {
        "id_album": "-1054518188",
        "link_thumb": "https://live.staticflickr.com/65535/51683524430_19c3361662_o.gif",
        "title": "One Piece Anime_L10"
      }
    ]
  },
  {
    "author": "adelenka",
    "link_thumb": "https://live.staticflickr.com/65535/51672423825_9bb22847db_o.gif",
    "link_bin": "https://github.com/lmbstudiocontact/mb4_1/raw/main/17572.bin",
    "id_bin": "17572",
    "list_language": [],
    "array_tags": [
      "digital",
      "date"
    ],
    "list_album": [
      {
        "id_album": "2433880",
        "link_thumb": "https://live.staticflickr.com/65535/51672423825_9bb22847db_o.gif",
        "title": "None"
      }
    ]
  },
  {
    "author": "minhdale",
    "link_thumb": "https://live.staticflickr.com/65535/51671677781_f1163c6ab6_o.gif",
    "link_bin": "https://github.com/lmbstudiocontact/mb4_21/raw/main/2046.bin",
    "id_bin": "2046",
    "list_language": [],
    "array_tags": [
      "pokemon",
      "pikachu"
    ],
    "list_album": [
      {
        "id_album": "63410260",
        "link_thumb": "https://live.staticflickr.com/65535/51671677781_f1163c6ab6_o.gif",
        "title": "Anime"
      }
    ]
  },
  {
    "author": "LMB Studio",
    "link_thumb": "https://live.staticflickr.com/65535/51686397946_495eb82a9b_o.gif",
    "link_bin": "https://github.com/lmbstudiocontact/mb4_72/raw/main/Pokmon Anime_L1_380600600.bin",
    "id_bin": "Pokmon Anime_L1_380600600",
    "list_language": [
      {
        "author": "LMB Studio",
        "link_thumb": "https://live.staticflickr.com/65535/51686480458_d532f311fe_o.gif",
        "link_bin": "https://github.com/lmbstudiocontact/mb4_72/raw/main/Pokmon Anime_L1_380600600_English.bin",
        "name_language": "English",
        "id_bin_language": "Pokmon Anime_L1_380600600_English"
      },
      {
        "author": "LMB Studio",
        "link_thumb": "https://live.staticflickr.com/65535/51687107480_838eb55e2b_o.gif",
        "link_bin": "https://github.com/lmbstudiocontact/mb4_72/raw/main/Pokmon Anime_L1_380600600_Portuguese.bin",
        "name_language": "Portuguese",
        "id_bin_language": "Pokmon Anime_L1_380600600_Portuguese"
      },
      {
        "author": "LMB Studio",
        "link_thumb": "https://live.staticflickr.com/65535/51686890039_2c0c0cf877_o.gif",
        "link_bin": "https://github.com/lmbstudiocontact/mb4_72/raw/main/Pokmon Anime_L1_380600600_Russian.bin",
        "name_language": "Russian",
        "id_bin_language": "Pokmon Anime_L1_380600600_Russian"
      },
      {
        "author": "LMB Studio",
        "link_thumb": "https://live.staticflickr.com/65535/51686890184_59c30ae1ff_o.gif",
        "link_bin": "https://github.com/lmbstudiocontact/mb4_72/raw/main/Pokmon Anime_L1_380600600_Spanish.bin",
        "name_language": "Spanish",
        "id_bin_language": "Pokmon Anime_L1_380600600_Spanish"
      }
    ],
    "array_tags": [
      "lmbstudio"
    ],
    "list_album": [
      {
        "id_album": "-555824144",
        "link_thumb": "https://live.staticflickr.com/65535/51686397946_495eb82a9b_o.gif",
        "title": "Pokmon Anime_L1"
      }
    ]
  },
  {
    "author": "LMB Studio",
    "link_thumb": "https://live.staticflickr.com/65535/51688422139_2afd57ce8a_o.gif",
    "link_bin": "https://github.com/lmbstudiocontact/mb4_79/raw/main/Ragnarok_L10_-1708898646.bin",
    "id_bin": "Ragnarok_L10_-1708898646",
    "list_language": [
      {
        "author": "LMB Studio",
        "link_thumb": "https://live.staticflickr.com/65535/51688642510_9444822f1a_o.gif",
        "link_bin": "https://github.com/lmbstudiocontact/mb4_79/raw/main/Ragnarok_L10_-1708898646_English.bin",
        "name_language": "English",
        "id_bin_language": "Ragnarok_L10_-1708898646_English"
      },
      {
        "author": "LMB Studio",
        "link_thumb": "https://live.staticflickr.com/65535/51688016833_0f6d41543e_o.gif",
        "link_bin": "https://github.com/lmbstudiocontact/mb4_79/raw/main/Ragnarok_L10_-1708898646_Portuguese.bin",
        "name_language": "Portuguese",
        "id_bin_language": "Ragnarok_L10_-1708898646_Portuguese"
      },
      {
        "author": "LMB Studio",
        "link_thumb": "https://live.staticflickr.com/65535/51688642840_48186a97e4_o.gif",
        "link_bin": "https://github.com/lmbstudiocontact/mb4_79/raw/main/Ragnarok_L10_-1708898646_Russian.bin",
        "name_language": "Russian",
        "id_bin_language": "Ragnarok_L10_-1708898646_Russian"
      },
      {
        "author": "LMB Studio",
        "link_thumb": "https://live.staticflickr.com/65535/51688017178_18b2757d5f_o.gif",
        "link_bin": "https://github.com/lmbstudiocontact/mb4_79/raw/main/Ragnarok_L10_-1708898646_Spanish.bin",
        "name_language": "Spanish",
        "id_bin_language": "Ragnarok_L10_-1708898646_Spanish"
      }
    ],
    "array_tags": [
      "lmbstudio"
    ],
    "list_album": [
      {
        "id_album": "-1898619025",
        "link_thumb": "https://live.staticflickr.com/65535/51688422139_2afd57ce8a_o.gif",
        "title": "Ragnarok_L10"
      }
    ]
  },
  {
    "author": "LMB Studio",
    "link_thumb": "https://live.staticflickr.com/65535/51678376088_685e6a9327_o.gif",
    "link_bin": "https://github.com/lmbstudiocontact/mb4_41/raw/main/Fox Art_L1_-403364692.bin",
    "id_bin": "Fox Art_L1_-403364692",
    "list_language": [
      {
        "author": "LMB Studio",
        "link_thumb": "https://live.staticflickr.com/65535/51678795944_73dac1696a_o.gif",
        "link_bin": "https://github.com/lmbstudiocontact/mb4_41/raw/main/Fox Art_L1_-403364692_English.bin",
        "name_language": "English",
        "id_bin_language": "Fox Art_L1_-403364692_English"
      },
      {
        "author": "LMB Studio",
        "link_thumb": "https://live.staticflickr.com/65535/51678796069_73e30e204c_o.gif",
        "link_bin": "https://github.com/lmbstudiocontact/mb4_41/raw/main/Fox Art_L1_-403364692_Portuguese.bin",
        "name_language": "Portuguese",
        "id_bin_language": "Fox Art_L1_-403364692_Portuguese"
      },
      {
        "author": "LMB Studio",
        "link_thumb": "https://live.staticflickr.com/65535/51678376438_48e4684c16_o.gif",
        "link_bin": "https://github.com/lmbstudiocontact/mb4_41/raw/main/Fox Art_L1_-403364692_Russian.bin",
        "name_language": "Russian",
        "id_bin_language": "Fox Art_L1_-403364692_Russian"
      },
      {
        "author": "LMB Studio",
        "link_thumb": "https://live.staticflickr.com/65535/51677322262_5153142bf0_o.gif",
        "link_bin": "https://github.com/lmbstudiocontact/mb4_41/raw/main/Fox Art_L1_-403364692_Spanish.bin",
        "name_language": "Spanish",
        "id_bin_language": "Fox Art_L1_-403364692_Spanish"
      }
    ],
    "array_tags": [
      "lmbstudio"
    ],
    "list_album": [
      {
        "id_album": "-646110862",
        "link_thumb": "https://live.staticflickr.com/65535/51678376088_685e6a9327_o.gif",
        "title": "Fox Art_L1"
      }
    ]
  },
  {
    "author": "LMB Studio",
    "link_thumb": "https://live.staticflickr.com/65535/51674435900_fcecbec609_o.gif",
    "link_bin": "https://github.com/lmbstudiocontact/mb4_13/raw/main/Couple_L6_528303862.bin",
    "id_bin": "Couple_L6_528303862",
    "list_language": [
      {
        "author": "LMB Studio",
        "link_thumb": "https://live.staticflickr.com/65535/51673801668_836fc204da_o.gif",
        "link_bin": "https://github.com/lmbstudiocontact/mb4_13/raw/main/Couple_L6_528303862_English.bin",
        "name_language": "English",
        "id_bin_language": "Couple_L6_528303862_English"
      },
      {
        "author": "LMB Studio",
        "link_thumb": "https://live.staticflickr.com/65535/51672759422_26be20f41d_o.gif",
        "link_bin": "https://github.com/lmbstudiocontact/mb4_13/raw/main/Couple_L6_528303862_Portuguese.bin",
        "name_language": "Portuguese",
        "id_bin_language": "Couple_L6_528303862_Portuguese"
      },
      {
        "author": "LMB Studio",
        "link_thumb": "https://live.staticflickr.com/65535/51674436260_f640b7d1a1_o.gif",
        "link_bin": "https://github.com/lmbstudiocontact/mb4_13/raw/main/Couple_L6_528303862_Russian.bin",
        "name_language": "Russian",
        "id_bin_language": "Couple_L6_528303862_Russian"
      },
      {
        "author": "LMB Studio",
        "link_thumb": "https://live.staticflickr.com/65535/51672759682_49781a6d65_o.gif",
        "link_bin": "https://github.com/lmbstudiocontact/mb4_13/raw/main/Couple_L6_528303862_Spanish.bin",
        "name_language": "Spanish",
        "id_bin_language": "Couple_L6_528303862_Spanish"
      }
    ],
    "array_tags": [
      "lmbstudio"
    ],
    "list_album": [
      {
        "id_album": "-888889815",
        "link_thumb": "https://live.staticflickr.com/65535/51674435900_fcecbec609_o.gif",
        "title": "Couple_L6"
      }
    ]
  },
  {
    "author": "LMB Studio",
    "link_thumb": "https://live.staticflickr.com/65535/51673555939_5991eafa58_o.gif",
    "link_bin": "https://github.com/lmbstudiocontact/mb4_12/raw/main/Animal Art_L3_2137488188.bin",
    "id_bin": "Animal Art_L3_2137488188",
    "list_language": [
      {
        "author": "LMB Studio",
        "link_thumb": "https://live.staticflickr.com/65535/51673752175_6cdbdfec92_o.gif",
        "link_bin": "https://github.com/lmbstudiocontact/mb4_12/raw/main/Animal Art_L3_2137488188_English.bin",
        "name_language": "English",
        "id_bin_language": "Animal Art_L3_2137488188_English"
      },
      {
        "author": "LMB Studio",
        "link_thumb": "https://live.staticflickr.com/65535/51673556404_0672aa05cd_o.gif",
        "link_bin": "https://github.com/lmbstudiocontact/mb4_12/raw/main/Animal Art_L3_2137488188_Portuguese.bin",
        "name_language": "Portuguese",
        "id_bin_language": "Animal Art_L3_2137488188_Portuguese"
      },
      {
        "author": "LMB Studio",
        "link_thumb": "https://live.staticflickr.com/65535/51673752560_b1af70f8e2_o.gif",
        "link_bin": "https://github.com/lmbstudiocontact/mb4_12/raw/main/Animal Art_L3_2137488188_Russian.bin",
        "name_language": "Russian",
        "id_bin_language": "Animal Art_L3_2137488188_Russian"
      },
      {
        "author": "LMB Studio",
        "link_thumb": "https://live.staticflickr.com/65535/51672881886_f5920fc3d7_o.gif",
        "link_bin": "https://github.com/lmbstudiocontact/mb4_12/raw/main/Animal Art_L3_2137488188_Spanish.bin",
        "name_language": "Spanish",
        "id_bin_language": "Animal Art_L3_2137488188_Spanish"
      }
    ],
    "array_tags": [
      "lmbstudio"
    ],
    "list_album": [
      {
        "id_album": "97007463",
        "link_thumb": "https://live.staticflickr.com/65535/51673555939_5991eafa58_o.gif",
        "title": "Animal Art_L3"
      }
    ]
  },
  {
    "author": "LMB Studio",
    "link_thumb": "https://live.staticflickr.com/65535/51688526012_f9b510b975_o.gif",
    "link_bin": "https://github.com/lmbstudiocontact/mb4_32/raw/main/Spider Man Cartoon_L9_718511411.bin",
    "id_bin": "Spider Man Cartoon_L9_718511411",
    "list_language": [
      {
        "author": "LMB Studio",
        "link_thumb": "https://live.staticflickr.com/65535/51689994904_c78bc00982_o.gif",
        "link_bin": "https://github.com/lmbstudiocontact/mb4_32/raw/main/Spider Man Cartoon_L9_718511411_English.bin",
        "name_language": "English",
        "id_bin_language": "Spider Man Cartoon_L9_718511411_English"
      },
      {
        "author": "LMB Studio",
        "link_thumb": "https://live.staticflickr.com/65535/51689316831_7c14d458ec_o.gif",
        "link_bin": "https://github.com/lmbstudiocontact/mb4_32/raw/main/Spider Man Cartoon_L9_718511411_Portuguese.bin",
        "name_language": "Portuguese",
        "id_bin_language": "Spider Man Cartoon_L9_718511411_Portuguese"
      },
      {
        "author": "LMB Studio",
        "link_thumb": "https://live.staticflickr.com/65535/51688526527_7192b5e6c8_o.gif",
        "link_bin": "https://github.com/lmbstudiocontact/mb4_32/raw/main/Spider Man Cartoon_L9_718511411_Russian.bin",
        "name_language": "Russian",
        "id_bin_language": "Spider Man Cartoon_L9_718511411_Russian"
      },
      {
        "author": "LMB Studio",
        "link_thumb": "https://live.staticflickr.com/65535/51688526722_bdbc25c175_o.gif",
        "link_bin": "https://github.com/lmbstudiocontact/mb4_32/raw/main/Spider Man Cartoon_L9_718511411_Spanish.bin",
        "name_language": "Spanish",
        "id_bin_language": "Spider Man Cartoon_L9_718511411_Spanish"
      }
    ],
    "array_tags": [
      "lmbstudio"
    ],
    "list_album": [
      {
        "id_album": "1735002399",
        "link_thumb": "https://live.staticflickr.com/65535/51688526012_f9b510b975_o.gif",
        "title": "Spider Man Cartoon_L9"
      }
    ]
  },
  {
    "author": "LMB Studio",
    "link_thumb": "https://live.staticflickr.com/65535/51688184861_df470d8dc9_o.gif",
    "link_bin": "https://github.com/lmbstudiocontact/mb4_26/raw/main/Seven deadly sins Anime_L4_-1564402699.bin",
    "id_bin": "Seven deadly sins Anime_L4_-1564402699",
    "list_language": [
      {
        "author": "LMB Studio",
        "link_thumb": "https://live.staticflickr.com/65535/51688185081_09f8b1ebf6_o.gif",
        "link_bin": "https://github.com/lmbstudiocontact/mb4_26/raw/main/Seven deadly sins Anime_L4_-1564402699_English.bin",
        "name_language": "English",
        "id_bin_language": "Seven deadly sins Anime_L4_-1564402699_English"
      },
      {
        "author": "LMB Studio",
        "link_thumb": "https://live.staticflickr.com/65535/51688457153_2012947445_o.gif",
        "link_bin": "https://github.com/lmbstudiocontact/mb4_26/raw/main/Seven deadly sins Anime_L4_-1564402699_Portuguese.bin",
        "name_language": "Portuguese",
        "id_bin_language": "Seven deadly sins Anime_L4_-1564402699_Portuguese"
      },
      {
        "author": "LMB Studio",
        "link_thumb": "https://live.staticflickr.com/65535/51688185481_cab1ed1dc2_o.gif",
        "link_bin": "https://github.com/lmbstudiocontact/mb4_26/raw/main/Seven deadly sins Anime_L4_-1564402699_Russian.bin",
        "name_language": "Russian",
        "id_bin_language": "Seven deadly sins Anime_L4_-1564402699_Russian"
      },
      {
        "author": "LMB Studio",
        "link_thumb": "https://live.staticflickr.com/65535/51688185866_075a7febd0_o.gif",
        "link_bin": "https://github.com/lmbstudiocontact/mb4_26/raw/main/Seven deadly sins Anime_L4_-1564402699_Spanish.bin",
        "name_language": "Spanish",
        "id_bin_language": "Seven deadly sins Anime_L4_-1564402699_Spanish"
      }
    ],
    "array_tags": [
      "lmbstudio"
    ],
    "list_album": [
      {
        "id_album": "1802210940",
        "link_thumb": "https://live.staticflickr.com/65535/51688184861_df470d8dc9_o.gif",
        "title": "Seven deadly sins Anime_L4"
      }
    ]
  },
  {
    "author": "LMB Studio",
    "link_thumb": "https://live.staticflickr.com/65535/51681030416_960e0d9a74_o.gif",
    "link_bin": "https://github.com/lmbstudiocontact/mb4_53/raw/main/Lilo \u0026 Stitch Cartoon_L6_-626404325.bin",
    "id_bin": "Lilo \u0026 Stitch Cartoon_L6_-626404325",
    "list_language": [
      {
        "author": "LMB Studio",
        "link_thumb": "https://live.staticflickr.com/65535/51681030606_8064f8a1d3_o.gif",
        "link_bin": "https://github.com/lmbstudiocontact/mb4_53/raw/main/Lilo \u0026 Stitch Cartoon_L6_-626404325_English.bin",
        "name_language": "English",
        "id_bin_language": "Lilo \u0026 Stitch Cartoon_L6_-626404325_English"
      },
      {
        "author": "LMB Studio",
        "link_thumb": "https://live.staticflickr.com/65535/51681030776_28211fc0bc_o.gif",
        "link_bin": "https://github.com/lmbstudiocontact/mb4_53/raw/main/Lilo \u0026 Stitch Cartoon_L6_-626404325_Portuguese.bin",
        "name_language": "Portuguese",
        "id_bin_language": "Lilo \u0026 Stitch Cartoon_L6_-626404325_Portuguese"
      },
      {
        "author": "LMB Studio",
        "link_thumb": "https://live.staticflickr.com/65535/51681287268_250413e040_o.gif",
        "link_bin": "https://github.com/lmbstudiocontact/mb4_53/raw/main/Lilo \u0026 Stitch Cartoon_L6_-626404325_Russian.bin",
        "name_language": "Russian",
        "id_bin_language": "Lilo \u0026 Stitch Cartoon_L6_-626404325_Russian"
      },
      {
        "author": "LMB Studio",
        "link_thumb": "https://live.staticflickr.com/65535/51681031026_31974a8880_o.gif",
        "link_bin": "https://github.com/lmbstudiocontact/mb4_53/raw/main/Lilo \u0026 Stitch Cartoon_L6_-626404325_Spanish.bin",
        "name_language": "Spanish",
        "id_bin_language": "Lilo \u0026 Stitch Cartoon_L6_-626404325_Spanish"
      }
    ],
    "array_tags": [
      "lmbstudio"
    ],
    "list_album": [
      {
        "id_album": "685543664",
        "link_thumb": "https://live.staticflickr.com/65535/51681030416_960e0d9a74_o.gif",
        "title": "Lilo \u0026 Stitch Cartoon_L6"
      }
    ]
  },
  {
    "author": "LMB Studio",
    "link_thumb": "https://live.staticflickr.com/65535/51674930086_15f815eea9_o.gif",
    "link_bin": "https://github.com/lmbstudiocontact/mb4_40/raw/main/Detective Conan_L1_-1997106533.bin",
    "id_bin": "Detective Conan_L1_-1997106533",
    "list_language": [
      {
        "author": "LMB Studio",
        "link_thumb": "https://live.staticflickr.com/65535/51674125797_d259c274d7_o.gif",
        "link_bin": "https://github.com/lmbstudiocontact/mb4_40/raw/main/Detective Conan_L1_-1997106533_English.bin",
        "name_language": "English",
        "id_bin_language": "Detective Conan_L1_-1997106533_English"
      },
      {
        "author": "LMB Studio",
        "link_thumb": "https://live.staticflickr.com/65535/51675168448_a288d80513_o.gif",
        "link_bin": "https://github.com/lmbstudiocontact/mb4_40/raw/main/Detective Conan_L1_-1997106533_Portuguese.bin",
        "name_language": "Portuguese",
        "id_bin_language": "Detective Conan_L1_-1997106533_Portuguese"
      },
      {
        "author": "LMB Studio",
        "link_thumb": "https://live.staticflickr.com/65535/51675168728_2529818195_o.gif",
        "link_bin": "https://github.com/lmbstudiocontact/mb4_40/raw/main/Detective Conan_L1_-1997106533_Russian.bin",
        "name_language": "Russian",
        "id_bin_language": "Detective Conan_L1_-1997106533_Russian"
      },
      {
        "author": "LMB Studio",
        "link_thumb": "https://live.staticflickr.com/65535/51674126612_e2e77fca31_o.gif",
        "link_bin": "https://github.com/lmbstudiocontact/mb4_40/raw/main/Detective Conan_L1_-1997106533_Spanish.bin",
        "name_language": "Spanish",
        "id_bin_language": "Detective Conan_L1_-1997106533_Spanish"
      }
    ],
    "array_tags": [
      "lmbstudio"
    ],
    "list_album": [
      {
        "id_album": "-1285383392",
        "link_thumb": "https://live.staticflickr.com/65535/51674930086_15f815eea9_o.gif",
        "title": "Detective Conan_L1"
      }
    ]
  },
  {
    "author": "shymik",
    "link_thumb": "https://live.staticflickr.com/65535/51670459612_bd50f4519e_o.gif",
    "link_bin": "https://github.com/lmbstudiocontact/mb4_0/raw/main/10678.bin",
    "id_bin": "10678",
    "list_language": [],
    "array_tags": [
      "digital",
      "date",
      "distance",
      "heartrate",
      "calories",
      "battery",
      "steps"
    ],
    "list_album": [
      {
        "id_album": "518493954",
        "link_thumb": "https://live.staticflickr.com/65535/51670459612_bd50f4519e_o.gif",
        "title": "Other 2"
      }
    ]
  },
  {
    "author": "LMB Studio",
    "link_thumb": "https://live.staticflickr.com/65535/51686197672_c69eaa9505_o.gif",
    "link_bin": "https://github.com/lmbstudiocontact/mb4_76/raw/main/Pokmon Anime_L5_-2051680806.bin",
    "id_bin": "Pokmon Anime_L5_-2051680806",
    "list_language": [
      {
        "author": "LMB Studio",
        "link_thumb": "https://live.staticflickr.com/65535/51686197897_e1919d5db7_o.gif",
        "link_bin": "https://github.com/lmbstudiocontact/mb4_76/raw/main/Pokmon Anime_L5_-2051680806_English.bin",
        "name_language": "English",
        "id_bin_language": "Pokmon Anime_L5_-2051680806_English"
      },
      {
        "author": "LMB Studio",
        "link_thumb": "https://live.staticflickr.com/65535/51686198112_cec8a4d10c_o.gif",
        "link_bin": "https://github.com/lmbstudiocontact/mb4_76/raw/main/Pokmon Anime_L5_-2051680806_Portuguese.bin",
        "name_language": "Portuguese",
        "id_bin_language": "Pokmon Anime_L5_-2051680806_Portuguese"
      },
      {
        "author": "LMB Studio",
        "link_thumb": "https://live.staticflickr.com/65535/51687667164_1cfeda1f9f_o.gif",
        "link_bin": "https://github.com/lmbstudiocontact/mb4_76/raw/main/Pokmon Anime_L5_-2051680806_Russian.bin",
        "name_language": "Russian",
        "id_bin_language": "Pokmon Anime_L5_-2051680806_Russian"
      },
      {
        "author": "LMB Studio",
        "link_thumb": "https://live.staticflickr.com/65535/51687667419_be1a36b16b_o.gif",
        "link_bin": "https://github.com/lmbstudiocontact/mb4_76/raw/main/Pokmon Anime_L5_-2051680806_Spanish.bin",
        "name_language": "Spanish",
        "id_bin_language": "Pokmon Anime_L5_-2051680806_Spanish"
      }
    ],
    "array_tags": [
      "lmbstudio"
    ],
    "list_album": [
      {
        "id_album": "-555824140",
        "link_thumb": "https://live.staticflickr.com/65535/51686197672_c69eaa9505_o.gif",
        "title": "Pokmon Anime_L5"
      }
    ]
  },
  {
    "author": "Sedative",
    "link_thumb": "https://live.staticflickr.com/65535/51674169546_467fcba20a_o.gif",
    "link_bin": "https://github.com/lmbstudiocontact/mb4_16/raw/main/19023.bin",
    "id_bin": "19023",
    "list_language": [],
    "array_tags": [
      "digital",
      "date",
      "distance",
      "heartrate",
      "calories",
      "battery",
      "steps"
    ],
    "list_album": [
      {
        "id_album": "-1956005621",
        "link_thumb": "https://live.staticflickr.com/65535/51674169546_467fcba20a_o.gif",
        "title": "None_2"
      }
    ]
  },
  {
    "author": "None",
    "link_thumb": "https://live.staticflickr.com/65535/51671909873_e11e5890df_o.gif",
    "link_bin": "https://github.com/lmbstudiocontact/mb4_21/raw/main/19433d78a6d86daedd614ae0df70c268.bin",
    "id_bin": "19433d78a6d86daedd614ae0df70c268",
    "list_language": [],
    "array_tags": [],
    "list_album": [
      {
        "id_album": "-810204084",
        "link_thumb": "https://live.staticflickr.com/65535/51671909873_e11e5890df_o.gif",
        "title": "Mi Watch Default"
      }
    ]
  },
  {
    "author": "gvb_it",
    "link_thumb": "https://live.staticflickr.com/65535/51672425806_41f6c8e480_o.gif",
    "link_bin": "https://github.com/lmbstudiocontact/mb4_25/raw/main/9010.bin",
    "id_bin": "9010",
    "list_language": [],
    "array_tags": [
      "digital",
      "date",
      "distance",
      "heartrate",
      "battery",
      "steps"
    ],
    "list_album": [
      {
        "id_album": "518493953",
        "link_thumb": "https://live.staticflickr.com/65535/51672425806_41f6c8e480_o.gif",
        "title": "Other 1"
      }
    ]
  },
  {
    "author": "LMB Studio",
    "link_thumb": "https://live.staticflickr.com/65535/51686644626_26717b6fec_o.gif",
    "link_bin": "https://github.com/lmbstudiocontact/mb4_73/raw/main/Pokmon Anime_L3_-2051623054.bin",
    "id_bin": "Pokmon Anime_L3_-2051623054",
    "list_language": [
      {
        "author": "LMB Studio",
        "link_thumb": "https://live.staticflickr.com/65535/51687326924_c33862809b_o.gif",
        "link_bin": "https://github.com/lmbstudiocontact/mb4_73/raw/main/Pokmon Anime_L3_-2051623054_English.bin",
        "name_language": "English",
        "id_bin_language": "Pokmon Anime_L3_-2051623054_English"
      },
      {
        "author": "LMB Studio",
        "link_thumb": "https://live.staticflickr.com/65535/51687327169_accbb5f258_o.gif",
        "link_bin": "https://github.com/lmbstudiocontact/mb4_73/raw/main/Pokmon Anime_L3_-2051623054_Portuguese.bin",
        "name_language": "Portuguese",
        "id_bin_language": "Pokmon Anime_L3_-2051623054_Portuguese"
      },
      {
        "author": "LMB Studio",
        "link_thumb": "https://live.staticflickr.com/65535/51686920418_5ddeff211b_o.gif",
        "link_bin": "https://github.com/lmbstudiocontact/mb4_73/raw/main/Pokmon Anime_L3_-2051623054_Russian.bin",
        "name_language": "Russian",
        "id_bin_language": "Pokmon Anime_L3_-2051623054_Russian"
      },
      {
        "author": "LMB Studio",
        "link_thumb": "https://live.staticflickr.com/65535/51686920723_e4977be8d7_o.gif",
        "link_bin": "https://github.com/lmbstudiocontact/mb4_73/raw/main/Pokmon Anime_L3_-2051623054_Spanish.bin",
        "name_language": "Spanish",
        "id_bin_language": "Pokmon Anime_L3_-2051623054_Spanish"
      }
    ],
    "array_tags": [
      "lmbstudio"
    ],
    "list_album": [
      {
        "id_album": "-555824142",
        "link_thumb": "https://live.staticflickr.com/65535/51686644626_26717b6fec_o.gif",
        "title": "Pokmon Anime_L3"
      }
    ]
  },
  {
    "author": "LMB Studio",
    "link_thumb": "https://live.staticflickr.com/65535/51675196847_1ca39cf034_o.gif",
    "link_bin": "https://github.com/lmbstudiocontact/mb4_74/raw/main/Dragon Ball Anime_L4_-1678843113.bin",
    "id_bin": "Dragon Ball Anime_L4_-1678843113",
    "list_language": [
      {
        "author": "LMB Studio",
        "link_thumb": "https://live.staticflickr.com/65535/51676672434_b7c6740d37_o.gif",
        "link_bin": "https://github.com/lmbstudiocontact/mb4_74/raw/main/Dragon Ball Anime_L4_-1678843113_English.bin",
        "name_language": "English",
        "id_bin_language": "Dragon Ball Anime_L4_-1678843113_English"
      },
      {
        "author": "LMB Studio",
        "link_thumb": "https://live.staticflickr.com/65535/51675998581_0bf34e25c4_o.gif",
        "link_bin": "https://github.com/lmbstudiocontact/mb4_74/raw/main/Dragon Ball Anime_L4_-1678843113_Portuguese.bin",
        "name_language": "Portuguese",
        "id_bin_language": "Dragon Ball Anime_L4_-1678843113_Portuguese"
      },
      {
        "author": "LMB Studio",
        "link_thumb": "https://live.staticflickr.com/65535/51676244223_b7a21e39cc_o.gif",
        "link_bin": "https://github.com/lmbstudiocontact/mb4_74/raw/main/Dragon Ball Anime_L4_-1678843113_Russian.bin",
        "name_language": "Russian",
        "id_bin_language": "Dragon Ball Anime_L4_-1678843113_Russian"
      },
      {
        "author": "LMB Studio",
        "link_thumb": "https://live.staticflickr.com/65535/51676244373_2d1f5c9415_o.gif",
        "link_bin": "https://github.com/lmbstudiocontact/mb4_74/raw/main/Dragon Ball Anime_L4_-1678843113_Spanish.bin",
        "name_language": "Spanish",
        "id_bin_language": "Dragon Ball Anime_L4_-1678843113_Spanish"
      }
    ],
    "array_tags": [
      "lmbstudio"
    ],
    "list_album": [
      {
        "id_album": "1464725223",
        "link_thumb": "https://live.staticflickr.com/65535/51675196847_1ca39cf034_o.gif",
        "title": "Dragon Ball Anime_L4"
      }
    ]
  },
  {
    "author": "toxicsquall",
    "link_thumb": "https://live.staticflickr.com/65535/51672894055_f242072506_o.gif",
    "link_bin": "https://github.com/lmbstudiocontact/mb4_66/raw/main/5062.bin",
    "id_bin": "5062",
    "list_language": [],
    "array_tags": [
      "game",
      "nintendo",
      "pokemon",
      "steps"
    ],
    "list_album": [
      {
        "id_album": "402419001",
        "link_thumb": "https://live.staticflickr.com/65535/51672894055_f242072506_o.gif",
        "title": "Anime_Animation"
      }
    ]
  },
  {
    "author": "LMB Studio",
    "link_thumb": "https://live.staticflickr.com/65535/51686171586_150ec8d7b2_o.gif",
    "link_bin": "https://github.com/lmbstudiocontact/mb4_72/raw/main/Pokmon Anime_L1_380597779.bin",
    "id_bin": "Pokmon Anime_L1_380597779",
    "list_language": [
      {
        "author": "LMB Studio",
        "link_thumb": "https://live.staticflickr.com/65535/51685387142_14fa5beb31_o.gif",
        "link_bin": "https://github.com/lmbstudiocontact/mb4_72/raw/main/Pokmon Anime_L1_380597779_English.bin",
        "name_language": "English",
        "id_bin_language": "Pokmon Anime_L1_380597779_English"
      },
      {
        "author": "LMB Studio",
        "link_thumb": "https://live.staticflickr.com/65535/51686172241_1da6fa1f15_o.gif",
        "link_bin": "https://github.com/lmbstudiocontact/mb4_72/raw/main/Pokmon Anime_L1_380597779_Portuguese.bin",
        "name_language": "Portuguese",
        "id_bin_language": "Pokmon Anime_L1_380597779_Portuguese"
      },
      {
        "author": "LMB Studio",
        "link_thumb": "https://live.staticflickr.com/65535/51687074160_b9db3c0b52_o.gif",
        "link_bin": "https://github.com/lmbstudiocontact/mb4_72/raw/main/Pokmon Anime_L1_380597779_Russian.bin",
        "name_language": "Russian",
        "id_bin_language": "Pokmon Anime_L1_380597779_Russian"
      },
      {
        "author": "LMB Studio",
        "link_thumb": "https://live.staticflickr.com/65535/51687074395_25b687de99_o.gif",
        "link_bin": "https://github.com/lmbstudiocontact/mb4_72/raw/main/Pokmon Anime_L1_380597779_Spanish.bin",
        "name_language": "Spanish",
        "id_bin_language": "Pokmon Anime_L1_380597779_Spanish"
      }
    ],
    "array_tags": [
      "lmbstudio"
    ],
    "list_album": [
      {
        "id_album": "-555824144",
        "link_thumb": "https://live.staticflickr.com/65535/51686171586_150ec8d7b2_o.gif",
        "title": "Pokmon Anime_L1"
      }
    ]
  },
  {
    "author": "LMB Studio",
    "link_thumb": "https://live.staticflickr.com/65535/51678878357_b182fe38a7_o.gif",
    "link_bin": "https://github.com/lmbstudiocontact/mb4_22/raw/main/Joker Harley Quinn_L3_-698016510.bin",
    "id_bin": "Joker Harley Quinn_L3_-698016510",
    "list_language": [
      {
        "author": "LMB Studio",
        "link_thumb": "https://live.staticflickr.com/65535/51678878817_e836430bb9_o.gif",
        "link_bin": "https://github.com/lmbstudiocontact/mb4_22/raw/main/Joker Harley Quinn_L3_-698016510_English.bin",
        "name_language": "English",
        "id_bin_language": "Joker Harley Quinn_L3_-698016510_English"
      },
      {
        "author": "LMB Studio",
        "link_thumb": "https://live.staticflickr.com/65535/51679681496_f2c25fd9d8_o.gif",
        "link_bin": "https://github.com/lmbstudiocontact/mb4_22/raw/main/Joker Harley Quinn_L3_-698016510_Portuguese.bin",
        "name_language": "Portuguese",
        "id_bin_language": "Joker Harley Quinn_L3_-698016510_Portuguese"
      },
      {
        "author": "LMB Studio",
        "link_thumb": "https://live.staticflickr.com/65535/51679681946_2238129b85_o.gif",
        "link_bin": "https://github.com/lmbstudiocontact/mb4_22/raw/main/Joker Harley Quinn_L3_-698016510_Russian.bin",
        "name_language": "Russian",
        "id_bin_language": "Joker Harley Quinn_L3_-698016510_Russian"
      },
      {
        "author": "LMB Studio",
        "link_thumb": "https://live.staticflickr.com/65535/51680355504_ea9e9ab33b_o.gif",
        "link_bin": "https://github.com/lmbstudiocontact/mb4_22/raw/main/Joker Harley Quinn_L3_-698016510_Spanish.bin",
        "name_language": "Spanish",
        "id_bin_language": "Joker Harley Quinn_L3_-698016510_Spanish"
      }
    ],
    "array_tags": [
      "lmbstudio"
    ],
    "list_album": [
      {
        "id_album": "-2022175635",
        "link_thumb": "https://live.staticflickr.com/65535/51678878357_b182fe38a7_o.gif",
        "title": "Joker Harley Quinn_L3"
      }
    ]
  },
  {
    "author": "Toan",
    "link_thumb": "https://live.staticflickr.com/65535/51673622822_8d7f8bd7f1_o.gif",
    "link_bin": "https://github.com/lmbstudiocontact/mb4_49/raw/main/20764.bin",
    "id_bin": "20764",
    "list_language": [],
    "array_tags": [
      "digital",
      "date",
      "bluetooth",
      "lock",
      "battery",
      "steps"
    ],
    "list_album": [
      {
        "id_album": "-2075887794",
        "link_thumb": "https://live.staticflickr.com/65535/51673622822_8d7f8bd7f1_o.gif",
        "title": "Cartoon"
      }
    ]
  },
  {
    "author": "LMB Studio",
    "link_thumb": "https://live.staticflickr.com/65535/51681693750_002536b5ff_o.gif",
    "link_bin": "https://github.com/lmbstudiocontact/mb4_51/raw/main/Kitty \u0026 My Melody_L9_254456317.bin",
    "id_bin": "Kitty \u0026 My Melody_L9_254456317",
    "list_language": [
      {
        "author": "LMB Studio",
        "link_thumb": "https://live.staticflickr.com/65535/51681067188_2d0926b188_o.gif",
        "link_bin": "https://github.com/lmbstudiocontact/mb4_51/raw/main/Kitty \u0026 My Melody_L9_254456317_English.bin",
        "name_language": "English",
        "id_bin_language": "Kitty \u0026 My Melody_L9_254456317_English"
      },
      {
        "author": "LMB Studio",
        "link_thumb": "https://live.staticflickr.com/65535/51681067358_c1466e6a08_o.gif",
        "link_bin": "https://github.com/lmbstudiocontact/mb4_51/raw/main/Kitty \u0026 My Melody_L9_254456317_Portuguese.bin",
        "name_language": "Portuguese",
        "id_bin_language": "Kitty \u0026 My Melody_L9_254456317_Portuguese"
      },
      {
        "author": "LMB Studio",
        "link_thumb": "https://live.staticflickr.com/65535/51681067578_28bb8b740f_o.gif",
        "link_bin": "https://github.com/lmbstudiocontact/mb4_51/raw/main/Kitty \u0026 My Melody_L9_254456317_Russian.bin",
        "name_language": "Russian",
        "id_bin_language": "Kitty \u0026 My Melody_L9_254456317_Russian"
      },
      {
        "author": "LMB Studio",
        "link_thumb": "https://live.staticflickr.com/65535/51681694405_685c92a3a6_o.gif",
        "link_bin": "https://github.com/lmbstudiocontact/mb4_51/raw/main/Kitty \u0026 My Melody_L9_254456317_Spanish.bin",
        "name_language": "Spanish",
        "id_bin_language": "Kitty \u0026 My Melody_L9_254456317_Spanish"
      }
    ],
    "array_tags": [
      "lmbstudio"
    ],
    "list_album": [
      {
        "id_album": "-378480537",
        "link_thumb": "https://live.staticflickr.com/65535/51681693750_002536b5ff_o.gif",
        "title": "Kitty \u0026 My Melody_L9"
      }
    ]
  },
  {
    "author": "LMB Studio",
    "link_thumb": "https://live.staticflickr.com/65535/51675788025_bf58a7a169_o.gif",
    "link_bin": "https://github.com/lmbstudiocontact/mb4_40/raw/main/Detective Conan_L10_530719899.bin",
    "id_bin": "Detective Conan_L10_530719899",
    "list_language": [
      {
        "author": "LMB Studio",
        "link_thumb": "https://live.staticflickr.com/65535/51675586854_7d16ebb4fc_o.gif",
        "link_bin": "https://github.com/lmbstudiocontact/mb4_40/raw/main/Detective Conan_L10_530719899_English.bin",
        "name_language": "English",
        "id_bin_language": "Detective Conan_L10_530719899_English"
      },
      {
        "author": "LMB Studio",
        "link_thumb": "https://live.staticflickr.com/65535/51675154843_e0721e4020_o.gif",
        "link_bin": "https://github.com/lmbstudiocontact/mb4_40/raw/main/Detective Conan_L10_530719899_Portuguese.bin",
        "name_language": "Portuguese",
        "id_bin_language": "Detective Conan_L10_530719899_Portuguese"
      },
      {
        "author": "LMB Studio",
        "link_thumb": "https://live.staticflickr.com/65535/51675788870_a06600b681_o.gif",
        "link_bin": "https://github.com/lmbstudiocontact/mb4_40/raw/main/Detective Conan_L10_530719899_Russian.bin",
        "name_language": "Russian",
        "id_bin_language": "Detective Conan_L10_530719899_Russian"
      },
      {
        "author": "LMB Studio",
        "link_thumb": "https://live.staticflickr.com/65535/51675155428_dcf86d4baa_o.gif",
        "link_bin": "https://github.com/lmbstudiocontact/mb4_40/raw/main/Detective Conan_L10_530719899_Spanish.bin",
        "name_language": "Spanish",
        "id_bin_language": "Detective Conan_L10_530719899_Spanish"
      }
    ],
    "array_tags": [
      "lmbstudio"
    ],
    "list_album": [
      {
        "id_album": "-1192179440",
        "link_thumb": "https://live.staticflickr.com/65535/51675788025_bf58a7a169_o.gif",
        "title": "Detective Conan_L10"
      }
    ]
  },
  {
    "author": "LMB Studio",
    "link_thumb": "https://live.staticflickr.com/65535/51686186590_b45d345782_o.gif",
    "link_bin": "https://github.com/lmbstudiocontact/mb4_67/raw/main/One Piece Anime_L8_1722712634.bin",
    "id_bin": "One Piece Anime_L8_1722712634",
    "list_language": [
      {
        "author": "LMB Studio",
        "link_thumb": "https://live.staticflickr.com/65535/51686186970_f9bb9c4c0e_o.gif",
        "link_bin": "https://github.com/lmbstudiocontact/mb4_67/raw/main/One Piece Anime_L8_1722712634_English.bin",
        "name_language": "English",
        "id_bin_language": "One Piece Anime_L8_1722712634_English"
      },
      {
        "author": "LMB Studio",
        "link_thumb": "https://live.staticflickr.com/65535/51684500007_d86e26b259_o.gif",
        "link_bin": "https://github.com/lmbstudiocontact/mb4_67/raw/main/One Piece Anime_L8_1722712634_Portuguese.bin",
        "name_language": "Portuguese",
        "id_bin_language": "One Piece Anime_L8_1722712634_Portuguese"
      },
      {
        "author": "LMB Studio",
        "link_thumb": "https://live.staticflickr.com/65535/51686187560_59ae4bd2c9_o.gif",
        "link_bin": "https://github.com/lmbstudiocontact/mb4_67/raw/main/One Piece Anime_L8_1722712634_Russian.bin",
        "name_language": "Russian",
        "id_bin_language": "One Piece Anime_L8_1722712634_Russian"
      },
      {
        "author": "LMB Studio",
        "link_thumb": "https://live.staticflickr.com/65535/51684500457_b9d6d91272_o.gif",
        "link_bin": "https://github.com/lmbstudiocontact/mb4_67/raw/main/One Piece Anime_L8_1722712634_Spanish.bin",
        "name_language": "Spanish",
        "id_bin_language": "One Piece Anime_L8_1722712634_Spanish"
      }
    ],
    "array_tags": [
      "lmbstudio"
    ],
    "list_album": [
      {
        "id_album": "1351456611",
        "link_thumb": "https://live.staticflickr.com/65535/51686186590_b45d345782_o.gif",
        "title": "One Piece Anime_L8"
      }
    ]
  },
  {
    "author": "brunello",
    "link_thumb": "https://live.staticflickr.com/65535/51674384056_e1f2a1db8e_o.gif",
    "link_bin": "https://github.com/lmbstudiocontact/mb4_48/raw/main/20459.bin",
    "id_bin": "20459",
    "list_language": [],
    "array_tags": [
      "date",
      "seconds",
      "heartrate",
      "steps"
    ],
    "list_album": [
      {
        "id_album": "-1956005621",
        "link_thumb": "https://live.staticflickr.com/65535/51674384056_e1f2a1db8e_o.gif",
        "title": "None_2"
      }
    ]
  },
  {
    "author": "LMB Studio",
    "link_thumb": "https://live.staticflickr.com/65535/51689983830_0d51999aa2_o.gif",
    "link_bin": "https://github.com/lmbstudiocontact/mb4_31/raw/main/Smurf Houses Cartoon_L5_1768755253.bin",
    "id_bin": "Smurf Houses Cartoon_L5_1768755253",
    "list_language": [
      {
        "author": "LMB Studio",
        "link_thumb": "https://live.staticflickr.com/65535/51689088806_9ea25c505d_o.gif",
        "link_bin": "https://github.com/lmbstudiocontact/mb4_31/raw/main/Smurf Houses Cartoon_L5_1768755253_English.bin",
        "name_language": "English",
        "id_bin_language": "Smurf Houses Cartoon_L5_1768755253_English"
      },
      {
        "author": "LMB Studio",
        "link_thumb": "https://live.staticflickr.com/65535/51689359523_4106265f0e_o.gif",
        "link_bin": "https://github.com/lmbstudiocontact/mb4_31/raw/main/Smurf Houses Cartoon_L5_1768755253_Portuguese.bin",
        "name_language": "Portuguese",
        "id_bin_language": "Smurf Houses Cartoon_L5_1768755253_Portuguese"
      },
      {
        "author": "LMB Studio",
        "link_thumb": "https://live.staticflickr.com/65535/51688299922_f2607e7396_o.gif",
        "link_bin": "https://github.com/lmbstudiocontact/mb4_31/raw/main/Smurf Houses Cartoon_L5_1768755253_Russian.bin",
        "name_language": "Russian",
        "id_bin_language": "Smurf Houses Cartoon_L5_1768755253_Russian"
      },
      {
        "author": "LMB Studio",
        "link_thumb": "https://live.staticflickr.com/65535/51688300182_ec27e863f7_o.gif",
        "link_bin": "https://github.com/lmbstudiocontact/mb4_31/raw/main/Smurf Houses Cartoon_L5_1768755253_Spanish.bin",
        "name_language": "Spanish",
        "id_bin_language": "Smurf Houses Cartoon_L5_1768755253_Spanish"
      }
    ],
    "array_tags": [
      "lmbstudio"
    ],
    "list_album": [
      {
        "id_album": "228264854",
        "link_thumb": "https://live.staticflickr.com/65535/51689983830_0d51999aa2_o.gif",
        "title": "Smurf Houses Cartoon_L5"
      }
    ]
  },
  {
    "author": "Subbota_kot",
    "link_thumb": "https://live.staticflickr.com/65535/51674426201_f00f21e2e3_o.gif",
    "link_bin": "https://github.com/lmbstudiocontact/mb4_49/raw/main/20719.bin",
    "id_bin": "20719",
    "list_language": [],
    "array_tags": [
      "digital",
      "date",
      "heartrate",
      "steps"
    ],
    "list_album": [
      {
        "id_album": "-1956005621",
        "link_thumb": "https://live.staticflickr.com/65535/51674426201_f00f21e2e3_o.gif",
        "title": "None_2"
      }
    ]
  },
  {
    "author": "LMB Studio",
    "link_thumb": "https://live.staticflickr.com/65535/51681305373_45cce1aa43_o.gif",
    "link_bin": "https://github.com/lmbstudiocontact/mb4_53/raw/main/Lilo \u0026 Stitch Cartoon_L8_-1144993004.bin",
    "id_bin": "Lilo \u0026 Stitch Cartoon_L8_-1144993004",
    "list_language": [
      {
        "author": "LMB Studio",
        "link_thumb": "https://live.staticflickr.com/65535/51681305543_16f8260651_o.gif",
        "link_bin": "https://github.com/lmbstudiocontact/mb4_53/raw/main/Lilo \u0026 Stitch Cartoon_L8_-1144993004_English.bin",
        "name_language": "English",
        "id_bin_language": "Lilo \u0026 Stitch Cartoon_L8_-1144993004_English"
      },
      {
        "author": "LMB Studio",
        "link_thumb": "https://live.staticflickr.com/65535/51681931620_42ac018154_o.gif",
        "link_bin": "https://github.com/lmbstudiocontact/mb4_53/raw/main/Lilo \u0026 Stitch Cartoon_L8_-1144993004_Portuguese.bin",
        "name_language": "Portuguese",
        "id_bin_language": "Lilo \u0026 Stitch Cartoon_L8_-1144993004_Portuguese"
      },
      {
        "author": "LMB Studio",
        "link_thumb": "https://live.staticflickr.com/65535/51681048701_72e0b22766_o.gif",
        "link_bin": "https://github.com/lmbstudiocontact/mb4_53/raw/main/Lilo \u0026 Stitch Cartoon_L8_-1144993004_Russian.bin",
        "name_language": "Russian",
        "id_bin_language": "Lilo \u0026 Stitch Cartoon_L8_-1144993004_Russian"
      },
      {
        "author": "LMB Studio",
        "link_thumb": "https://live.staticflickr.com/65535/51681720874_e9380ab0ed_o.gif",
        "link_bin": "https://github.com/lmbstudiocontact/mb4_53/raw/main/Lilo \u0026 Stitch Cartoon_L8_-1144993004_Spanish.bin",
        "name_language": "Spanish",
        "id_bin_language": "Lilo \u0026 Stitch Cartoon_L8_-1144993004_Spanish"
      }
    ],
    "array_tags": [
      "lmbstudio"
    ],
    "list_album": [
      {
        "id_album": "685543666",
        "link_thumb": "https://live.staticflickr.com/65535/51681305373_45cce1aa43_o.gif",
        "title": "Lilo \u0026 Stitch Cartoon_L8"
      }
    ]
  },
  {
    "author": "LMB Studio",
    "link_thumb": "https://live.staticflickr.com/65535/51686786117_0309eb120f_o.gif",
    "link_bin": "https://github.com/lmbstudiocontact/mb4_78/raw/main/Raccoons_L2_-403364692.bin",
    "id_bin": "Raccoons_L2_-403364692",
    "list_language": [
      {
        "author": "LMB Studio",
        "link_thumb": "https://live.staticflickr.com/65535/51688476410_65df1faf9d_o.gif",
        "link_bin": "https://github.com/lmbstudiocontact/mb4_78/raw/main/Raccoons_L2_-403364692_English.bin",
        "name_language": "English",
        "id_bin_language": "Raccoons_L2_-403364692_English"
      },
      {
        "author": "LMB Studio",
        "link_thumb": "https://live.staticflickr.com/65535/51687851218_e6c978835b_o.gif",
        "link_bin": "https://github.com/lmbstudiocontact/mb4_78/raw/main/Raccoons_L2_-403364692_Portuguese.bin",
        "name_language": "Portuguese",
        "id_bin_language": "Raccoons_L2_-403364692_Portuguese"
      },
      {
        "author": "LMB Studio",
        "link_thumb": "https://live.staticflickr.com/65535/51688476910_d9cdb4e7d2_o.gif",
        "link_bin": "https://github.com/lmbstudiocontact/mb4_78/raw/main/Raccoons_L2_-403364692_Russian.bin",
        "name_language": "Russian",
        "id_bin_language": "Raccoons_L2_-403364692_Russian"
      },
      {
        "author": "LMB Studio",
        "link_thumb": "https://live.staticflickr.com/65535/51687851678_d78b2356fb_o.gif",
        "link_bin": "https://github.com/lmbstudiocontact/mb4_78/raw/main/Raccoons_L2_-403364692_Spanish.bin",
        "name_language": "Spanish",
        "id_bin_language": "Raccoons_L2_-403364692_Spanish"
      }
    ],
    "array_tags": [
      "lmbstudio"
    ],
    "list_album": [
      {
        "id_album": "1998705265",
        "link_thumb": "https://live.staticflickr.com/65535/51686786117_0309eb120f_o.gif",
        "title": "Raccoons_L2"
      }
    ]
  },
  {
    "author": "GPS",
    "link_thumb": "https://live.staticflickr.com/65535/51671259611_4bd8313afb_o.gif",
    "link_bin": "https://github.com/lmbstudiocontact/mb4_0/raw/main/10632.bin",
    "id_bin": "10632",
    "list_language": [],
    "array_tags": [
      "digital",
      "date",
      "distance",
      "heartrate",
      "calories",
      "battery",
      "steps"
    ],
    "list_album": [
      {
        "id_album": "63410260",
        "link_thumb": "https://live.staticflickr.com/65535/51671259611_4bd8313afb_o.gif",
        "title": "Anime"
      }
    ]
  },
  {
    "author": "mad max",
    "link_thumb": "https://live.staticflickr.com/65535/51670422232_e19460e6d8_o.gif",
    "link_bin": "https://github.com/lmbstudiocontact/mb4_0/raw/main/10248.bin",
    "id_bin": "10248",
    "list_language": [],
    "array_tags": [
      "digital",
      "date",
      "battery",
      "steps"
    ],
    "list_album": [
      {
        "id_album": "518493953",
        "link_thumb": "https://live.staticflickr.com/65535/51670422232_e19460e6d8_o.gif",
        "title": "Other 1"
      }
    ]
  },
  {
    "author": "LMB Studio",
    "link_thumb": "https://live.staticflickr.com/65535/51676566770_9766d05f36_o.gif",
    "link_bin": "https://github.com/lmbstudiocontact/mb4_19/raw/main/Dragon Art_L1_213949028.bin",
    "id_bin": "Dragon Art_L1_213949028",
    "list_language": [
      {
        "author": "LMB Studio",
        "link_thumb": "https://live.staticflickr.com/65535/51676566915_c25e7d2cee_o.gif",
        "link_bin": "https://github.com/lmbstudiocontact/mb4_19/raw/main/Dragon Art_L1_213949028_English.bin",
        "name_language": "English",
        "id_bin_language": "Dragon Art_L1_213949028_English"
      },
      {
        "author": "LMB Studio",
        "link_thumb": "https://live.staticflickr.com/65535/51676365504_65678c12e1_o.gif",
        "link_bin": "https://github.com/lmbstudiocontact/mb4_19/raw/main/Dragon Art_L1_213949028_Portuguese.bin",
        "name_language": "Portuguese",
        "id_bin_language": "Dragon Art_L1_213949028_Portuguese"
      },
      {
        "author": "LMB Studio",
        "link_thumb": "https://live.staticflickr.com/65535/51675690651_7cdffb12e5_o.gif",
        "link_bin": "https://github.com/lmbstudiocontact/mb4_19/raw/main/Dragon Art_L1_213949028_Russian.bin",
        "name_language": "Russian",
        "id_bin_language": "Dragon Art_L1_213949028_Russian"
      },
      {
        "author": "LMB Studio",
        "link_thumb": "https://live.staticflickr.com/65535/51676567555_275c066bda_o.gif",
        "link_bin": "https://github.com/lmbstudiocontact/mb4_19/raw/main/Dragon Art_L1_213949028_Spanish.bin",
        "name_language": "Spanish",
        "id_bin_language": "Dragon Art_L1_213949028_Spanish"
      }
    ],
    "array_tags": [
      "lmbstudio"
    ],
    "list_album": [
      {
        "id_album": "2059013998",
        "link_thumb": "https://live.staticflickr.com/65535/51676566770_9766d05f36_o.gif",
        "title": "Dragon Art_L1"
      }
    ]
  },
  {
    "author": "hard2explain",
    "link_thumb": "https://live.staticflickr.com/65535/51673353805_099ffae7a0_o.gif",
    "link_bin": "https://github.com/lmbstudiocontact/mb4_11/raw/main/9607.bin",
    "id_bin": "9607",
    "list_language": [],
    "array_tags": [
      "date",
      "digital",
      "minimal",
      "heartrate",
      "battery",
      "steps"
    ],
    "list_album": [
      {
        "id_album": "518493953",
        "link_thumb": "https://live.staticflickr.com/65535/51673353805_099ffae7a0_o.gif",
        "title": "Other 1"
      }
    ]
  },
  {
    "author": "LMB Studio",
    "link_thumb": "https://live.staticflickr.com/65535/51687094912_483d196c35_o.gif",
    "link_bin": "https://github.com/lmbstudiocontact/mb4_80/raw/main/Ratatouille Cartoon_L8_-472896530.bin",
    "id_bin": "Ratatouille Cartoon_L8_-472896530",
    "list_language": [
      {
        "author": "LMB Studio",
        "link_thumb": "https://live.staticflickr.com/65535/51687095032_47f52dafd4_o.gif",
        "link_bin": "https://github.com/lmbstudiocontact/mb4_80/raw/main/Ratatouille Cartoon_L8_-472896530_English.bin",
        "name_language": "English",
        "id_bin_language": "Ratatouille Cartoon_L8_-472896530_English"
      },
      {
        "author": "LMB Studio",
        "link_thumb": "https://live.staticflickr.com/65535/51687095172_6e91dddbf9_o.gif",
        "link_bin": "https://github.com/lmbstudiocontact/mb4_80/raw/main/Ratatouille Cartoon_L8_-472896530_Portuguese.bin",
        "name_language": "Portuguese",
        "id_bin_language": "Ratatouille Cartoon_L8_-472896530_Portuguese"
      },
      {
        "author": "LMB Studio",
        "link_thumb": "https://live.staticflickr.com/65535/51688565709_951254368d_o.gif",
        "link_bin": "https://github.com/lmbstudiocontact/mb4_80/raw/main/Ratatouille Cartoon_L8_-472896530_Russian.bin",
        "name_language": "Russian",
        "id_bin_language": "Ratatouille Cartoon_L8_-472896530_Russian"
      },
      {
        "author": "LMB Studio",
        "link_thumb": "https://live.staticflickr.com/65535/51688158448_269bce5791_o.gif",
        "link_bin": "https://github.com/lmbstudiocontact/mb4_80/raw/main/Ratatouille Cartoon_L8_-472896530_Spanish.bin",
        "name_language": "Spanish",
        "id_bin_language": "Ratatouille Cartoon_L8_-472896530_Spanish"
      }
    ],
    "array_tags": [
      "lmbstudio"
    ],
    "list_album": [
      {
        "id_album": "1746345507",
        "link_thumb": "https://live.staticflickr.com/65535/51687094912_483d196c35_o.gif",
        "title": "Ratatouille Cartoon_L8"
      }
    ]
  },
  {
    "author": "MEXResendiz",
    "link_thumb": "https://live.staticflickr.com/65535/51672725318_aa1ef592fc_o.gif",
    "link_bin": "https://github.com/lmbstudiocontact/mb4_11/raw/main/963.bin",
    "id_bin": "963",
    "list_language": [],
    "array_tags": [
      "evangelion",
      "anime"
    ],
    "list_album": [
      {
        "id_album": "518493955",
        "link_thumb": "https://live.staticflickr.com/65535/51672725318_aa1ef592fc_o.gif",
        "title": "Other 3"
      }
    ]
  },
  {
    "author": "njman69",
    "link_thumb": "https://live.staticflickr.com/65535/51670906617_fcdeabec99_o.gif",
    "link_bin": "https://github.com/lmbstudiocontact/mb4_21/raw/main/236.bin",
    "id_bin": "236",
    "list_language": [],
    "array_tags": [
      "digital"
    ],
    "list_album": [
      {
        "id_album": "-1997428321",
        "link_thumb": "https://live.staticflickr.com/65535/51670906617_fcdeabec99_o.gif",
        "title": "Marvel"
      }
    ]
  },
  {
    "author": "Proky666",
    "link_thumb": "https://live.staticflickr.com/65535/51673142005_6cc281c697_o.gif",
    "link_bin": "https://github.com/lmbstudiocontact/mb4_10/raw/main/7182.bin",
    "id_bin": "7182",
    "list_language": [],
    "array_tags": [
      "digital",
      "date",
      "heartrate",
      "battery",
      "steps"
    ],
    "list_album": [
      {
        "id_album": "65078219",
        "link_thumb": "https://live.staticflickr.com/65535/51673142005_6cc281c697_o.gif",
        "title": "Chibi"
      }
    ]
  },
  {
    "author": "LMB Studio",
    "link_thumb": "https://live.staticflickr.com/65535/51685713049_b36e5977ec_o.gif",
    "link_bin": "https://github.com/lmbstudiocontact/mb4_65/raw/main/One Piece Anime_L6_-1738760696.bin",
    "id_bin": "One Piece Anime_L6_-1738760696",
    "list_language": [
      {
        "author": "LMB Studio",
        "link_thumb": "https://live.staticflickr.com/65535/51685929790_c0f43e3df0_o.gif",
        "link_bin": "https://github.com/lmbstudiocontact/mb4_65/raw/main/One Piece Anime_L6_-1738760696_English.bin",
        "name_language": "English",
        "id_bin_language": "One Piece Anime_L6_-1738760696_English"
      },
      {
        "author": "LMB Studio",
        "link_thumb": "https://live.staticflickr.com/65535/51685929960_a5bb24942e_o.gif",
        "link_bin": "https://github.com/lmbstudiocontact/mb4_65/raw/main/One Piece Anime_L6_-1738760696_Portuguese.bin",
        "name_language": "Portuguese",
        "id_bin_language": "One Piece Anime_L6_-1738760696_Portuguese"
      },
      {
        "author": "LMB Studio",
        "link_thumb": "https://live.staticflickr.com/65535/51685029211_6b05c5c966_o.gif",
        "link_bin": "https://github.com/lmbstudiocontact/mb4_65/raw/main/One Piece Anime_L6_-1738760696_Russian.bin",
        "name_language": "Russian",
        "id_bin_language": "One Piece Anime_L6_-1738760696_Russian"
      },
      {
        "author": "LMB Studio",
        "link_thumb": "https://live.staticflickr.com/65535/51685713754_b233a826f7_o.gif",
        "link_bin": "https://github.com/lmbstudiocontact/mb4_65/raw/main/One Piece Anime_L6_-1738760696_Spanish.bin",
        "name_language": "Spanish",
        "id_bin_language": "One Piece Anime_L6_-1738760696_Spanish"
      }
    ],
    "array_tags": [
      "lmbstudio"
    ],
    "list_album": [
      {
        "id_album": "1351456609",
        "link_thumb": "https://live.staticflickr.com/65535/51685713049_b36e5977ec_o.gif",
        "title": "One Piece Anime_L6"
      }
    ]
  },
  {
    "author": "LMB Studio",
    "link_thumb": "https://live.staticflickr.com/65535/51688873996_07c57be991_o.gif",
    "link_bin": "https://github.com/lmbstudiocontact/mb4_30/raw/main/Shiv_L8_1464752249.bin",
    "id_bin": "Shiv_L8_1464752249",
    "list_language": [
      {
        "author": "LMB Studio",
        "link_thumb": "https://live.staticflickr.com/65535/51688085137_f18d572eeb_o.gif",
        "link_bin": "https://github.com/lmbstudiocontact/mb4_30/raw/main/Shiv_L8_1464752249_English.bin",
        "name_language": "English",
        "id_bin_language": "Shiv_L8_1464752249_English"
      },
      {
        "author": "LMB Studio",
        "link_thumb": "https://live.staticflickr.com/65535/51688875051_aee00017dd_o.gif",
        "link_bin": "https://github.com/lmbstudiocontact/mb4_30/raw/main/Shiv_L8_1464752249_Portuguese.bin",
        "name_language": "Portuguese",
        "id_bin_language": "Shiv_L8_1464752249_Portuguese"
      },
      {
        "author": "LMB Studio",
        "link_thumb": "https://live.staticflickr.com/65535/51689771810_21a319267d_o.gif",
        "link_bin": "https://github.com/lmbstudiocontact/mb4_30/raw/main/Shiv_L8_1464752249_Russian.bin",
        "name_language": "Russian",
        "id_bin_language": "Shiv_L8_1464752249_Russian"
      },
      {
        "author": "LMB Studio",
        "link_thumb": "https://live.staticflickr.com/65535/51689147053_631cec8930_o.gif",
        "link_bin": "https://github.com/lmbstudiocontact/mb4_30/raw/main/Shiv_L8_1464752249_Spanish.bin",
        "name_language": "Spanish",
        "id_bin_language": "Shiv_L8_1464752249_Spanish"
      }
    ],
    "array_tags": [
      "lmbstudio"
    ],
    "list_album": [
      {
        "id_album": "-568595351",
        "link_thumb": "https://live.staticflickr.com/65535/51688873996_07c57be991_o.gif",
        "title": "Shiv_L8"
      }
    ]
  },
  {
    "author": "NDL",
    "link_thumb": "https://live.staticflickr.com/65535/51672869974_cfd3854819_o.gif",
    "link_bin": "https://github.com/lmbstudiocontact/mb4_10/raw/main/6432.bin",
    "id_bin": "6432",
    "list_language": [],
    "array_tags": [
      "digital",
      "date",
      "distance",
      "heartrate",
      "battery",
      "steps"
    ],
    "list_album": [
      {
        "id_album": "518493955",
        "link_thumb": "https://live.staticflickr.com/65535/51672869974_cfd3854819_o.gif",
        "title": "Other 3"
      }
    ]
  },
  {
    "author": "Tarantula24",
    "link_thumb": "https://live.staticflickr.com/65535/51671887068_351986e57f_o.gif",
    "link_bin": "https://github.com/lmbstudiocontact/mb4_21/raw/main/18409.bin",
    "id_bin": "18409",
    "list_language": [],
    "array_tags": [
      "date",
      "bateria",
      "data",
      "battery",
      "steps",
      "kroki"
    ],
    "list_album": [
      {
        "id_album": "2433880",
        "link_thumb": "https://live.staticflickr.com/65535/51671887068_351986e57f_o.gif",
        "title": "None"
      }
    ]
  },
  {
    "author": "shymik",
    "link_thumb": "https://live.staticflickr.com/65535/51671925449_1f4da9aa8e_o.gif",
    "link_bin": "https://github.com/lmbstudiocontact/mb4_0/raw/main/10434.bin",
    "id_bin": "10434",
    "list_language": [],
    "array_tags": [
      "digital",
      "date",
      "distance",
      "heartrate",
      "calories",
      "battery",
      "steps"
    ],
    "list_album": [
      {
        "id_album": "518493953",
        "link_thumb": "https://live.staticflickr.com/65535/51671925449_1f4da9aa8e_o.gif",
        "title": "Other 1"
      }
    ]
  },
  {
    "author": "LMB Studio",
    "link_thumb": "https://live.staticflickr.com/65535/51675936256_ef9b58da65_o.gif",
    "link_bin": "https://github.com/lmbstudiocontact/mb4_8/raw/main/Dragon Ball Anime_L2_889283301.bin",
    "id_bin": "Dragon Ball Anime_L2_889283301",
    "list_language": [
      {
        "author": "LMB Studio",
        "link_thumb": "https://live.staticflickr.com/65535/51675135067_a35b239528_o.gif",
        "link_bin": "https://github.com/lmbstudiocontact/mb4_8/raw/main/Dragon Ball Anime_L2_889283301_English.bin",
        "name_language": "English",
        "id_bin_language": "Dragon Ball Anime_L2_889283301_English"
      },
      {
        "author": "LMB Studio",
        "link_thumb": "https://live.staticflickr.com/65535/51675135182_8e82fff00e_o.gif",
        "link_bin": "https://github.com/lmbstudiocontact/mb4_8/raw/main/Dragon Ball Anime_L2_889283301_Portuguese.bin",
        "name_language": "Portuguese",
        "id_bin_language": "Dragon Ball Anime_L2_889283301_Portuguese"
      },
      {
        "author": "LMB Studio",
        "link_thumb": "https://live.staticflickr.com/65535/51676814380_dacc2d765a_o.gif",
        "link_bin": "https://github.com/lmbstudiocontact/mb4_8/raw/main/Dragon Ball Anime_L2_889283301_Russian.bin",
        "name_language": "Russian",
        "id_bin_language": "Dragon Ball Anime_L2_889283301_Russian"
      },
      {
        "author": "LMB Studio",
        "link_thumb": "https://live.staticflickr.com/65535/51676609814_0174fcc58e_o.gif",
        "link_bin": "https://github.com/lmbstudiocontact/mb4_8/raw/main/Dragon Ball Anime_L2_889283301_Spanish.bin",
        "name_language": "Spanish",
        "id_bin_language": "Dragon Ball Anime_L2_889283301_Spanish"
      }
    ],
    "array_tags": [
      "lmbstudio"
    ],
    "list_album": [
      {
        "id_album": "1464725221",
        "link_thumb": "https://live.staticflickr.com/65535/51675936256_ef9b58da65_o.gif",
        "title": "Dragon Ball Anime_L2"
      }
    ]
  }
]